[ {
  "orderNo" : "00C4BB73",
  "orderStatus" : "INVALID",
  "orderValidationCode" : "CARD_NUMBER_INVALID",
  "costInPence" : 2500
}, {
  "orderNo" : "691593AB",
  "orderStatus" : "INVALID",
  "orderValidationCode" : "EXPIRY_DATE_INVALID",
  "costInPence" : 2600
}, {
  "orderNo" : "725D51B9",
  "orderStatus" : "INVALID",
  "orderValidationCode" : "CVV_INVALID",
  "costInPence" : 2400
}, {
  "orderNo" : "48CBD479",
  "orderStatus" : "INVALID",
  "orderValidationCode" : "TOTAL_INCORRECT",
  "costInPence" : 2436
}, {
  "orderNo" : "27E4ACB6",
  "orderStatus" : "INVALID",
  "orderValidationCode" : "PIZZA_NOT_DEFINED",
  "costInPence" : 2500
}, {
  "orderNo" : "2A85D93C",
  "orderStatus" : "INVALID",
  "orderValidationCode" : "PIZZA_NOT_DEFINED",
  "costInPence" : -1994808920
}, {
  "orderNo" : "17DAC1BE",
  "orderStatus" : "INVALID",
  "orderValidationCode" : "PIZZA_FROM_MULTIPLE_RESTAURANTS",
  "costInPence" : 3400
}, {
  "orderNo" : "1319159B",
  "orderStatus" : "INVALID",
  "orderValidationCode" : "RESTAURANT_CLOSED",
  "costInPence" : 1500
}, {
  "orderNo" : "4A4E79E9",
  "orderStatus" : "DELIVERED",
  "orderValidationCode" : "NO_ERROR",
  "costInPence" : 2400
}, {
  "orderNo" : "5A3D7C3D",
  "orderStatus" : "DELIVERED",
  "orderValidationCode" : "NO_ERROR",
  "costInPence" : 2400
}, {
  "orderNo" : "5B1D3514",
  "orderStatus" : "DELIVERED",
  "orderValidationCode" : "NO_ERROR",
  "costInPence" : 2500
}, {
  "orderNo" : "7F24AF12",
  "orderStatus" : "INVALID",
  "orderValidationCode" : "RESTAURANT_CLOSED",
  "costInPence" : 2600
}, {
  "orderNo" : "00BA717C",
  "orderStatus" : "DELIVERED",
  "orderValidationCode" : "NO_ERROR",
  "costInPence" : 2400
}, {
  "orderNo" : "38BE7197",
  "orderStatus" : "DELIVERED",
  "orderValidationCode" : "NO_ERROR",
  "costInPence" : 2400
}, {
  "orderNo" : "6EF47BDF",
  "orderStatus" : "DELIVERED",
  "orderValidationCode" : "NO_ERROR",
  "costInPence" : 2500
}, {
  "orderNo" : "34DAEDA1",
  "orderStatus" : "INVALID",
  "orderValidationCode" : "RESTAURANT_CLOSED",
  "costInPence" : 2600
}, {
  "orderNo" : "300C9A59",
  "orderStatus" : "DELIVERED",
  "orderValidationCode" : "NO_ERROR",
  "costInPence" : 2400
}, {
  "orderNo" : "165DBB6F",
  "orderStatus" : "DELIVERED",
  "orderValidationCode" : "NO_ERROR",
  "costInPence" : 2400
}, {
  "orderNo" : "26F1B5AD",
  "orderStatus" : "DELIVERED",
  "orderValidationCode" : "NO_ERROR",
  "costInPence" : 2500
}, {
  "orderNo" : "3B771C86",
  "orderStatus" : "INVALID",
  "orderValidationCode" : "RESTAURANT_CLOSED",
  "costInPence" : 2600
}, {
  "orderNo" : "53F545C1",
  "orderStatus" : "DELIVERED",
  "orderValidationCode" : "NO_ERROR",
  "costInPence" : 2400
}, {
  "orderNo" : "1A485232",
  "orderStatus" : "DELIVERED",
  "orderValidationCode" : "NO_ERROR",
  "costInPence" : 2400
}, {
  "orderNo" : "1FA32289",
  "orderStatus" : "DELIVERED",
  "orderValidationCode" : "NO_ERROR",
  "costInPence" : 2500
}, {
  "orderNo" : "5D8A5545",
  "orderStatus" : "INVALID",
  "orderValidationCode" : "RESTAURANT_CLOSED",
  "costInPence" : 2600
}, {
  "orderNo" : "1296ED89",
  "orderStatus" : "DELIVERED",
  "orderValidationCode" : "NO_ERROR",
  "costInPence" : 2400
}, {
  "orderNo" : "29FE28F7",
  "orderStatus" : "DELIVERED",
  "orderValidationCode" : "NO_ERROR",
  "costInPence" : 2400
}, {
  "orderNo" : "1C2F09C5",
  "orderStatus" : "DELIVERED",
  "orderValidationCode" : "NO_ERROR",
  "costInPence" : 2500
}, {
  "orderNo" : "1CA13073",
  "orderStatus" : "INVALID",
  "orderValidationCode" : "RESTAURANT_CLOSED",
  "costInPence" : 2600
}, {
  "orderNo" : "65DDF409",
  "orderStatus" : "DELIVERED",
  "orderValidationCode" : "NO_ERROR",
  "costInPence" : 2400
}, {
  "orderNo" : "386B050A",
  "orderStatus" : "DELIVERED",
  "orderValidationCode" : "NO_ERROR",
  "costInPence" : 2400
}, {
  "orderNo" : "07C8CF22",
  "orderStatus" : "DELIVERED",
  "orderValidationCode" : "NO_ERROR",
  "costInPence" : 2500
}, {
  "orderNo" : "59F655AA",
  "orderStatus" : "INVALID",
  "orderValidationCode" : "RESTAURANT_CLOSED",
  "costInPence" : 2600
}, {
  "orderNo" : "21462A2E",
  "orderStatus" : "DELIVERED",
  "orderValidationCode" : "NO_ERROR",
  "costInPence" : 2400
}, {
  "orderNo" : "62F14CE7",
  "orderStatus" : "DELIVERED",
  "orderValidationCode" : "NO_ERROR",
  "costInPence" : 2400
}, {
  "orderNo" : "6E7B9781",
  "orderStatus" : "DELIVERED",
  "orderValidationCode" : "NO_ERROR",
  "costInPence" : 2500
}, {
  "orderNo" : "1E73FF1E",
  "orderStatus" : "INVALID",
  "orderValidationCode" : "RESTAURANT_CLOSED",
  "costInPence" : 2600
}, {
  "orderNo" : "0F76B8A9",
  "orderStatus" : "DELIVERED",
  "orderValidationCode" : "NO_ERROR",
  "costInPence" : 2400
}, {
  "orderNo" : "19790D04",
  "orderStatus" : "DELIVERED",
  "orderValidationCode" : "NO_ERROR",
  "costInPence" : 2400
}, {
  "orderNo" : "269BF5C1",
  "orderStatus" : "DELIVERED",
  "orderValidationCode" : "NO_ERROR",
  "costInPence" : 2500
}, {
  "orderNo" : "392FECB5",
  "orderStatus" : "INVALID",
  "orderValidationCode" : "RESTAURANT_CLOSED",
  "costInPence" : 2600
}, {
  "orderNo" : "79EED77D",
  "orderStatus" : "DELIVERED",
  "orderValidationCode" : "NO_ERROR",
  "costInPence" : 2400
}, {
  "orderNo" : "7171355D",
  "orderStatus" : "DELIVERED",
  "orderValidationCode" : "NO_ERROR",
  "costInPence" : 2400
}, {
  "orderNo" : "438A2D65",
  "orderStatus" : "DELIVERED",
  "orderValidationCode" : "NO_ERROR",
  "costInPence" : 2500
}, {
  "orderNo" : "74441E58",
  "orderStatus" : "INVALID",
  "orderValidationCode" : "RESTAURANT_CLOSED",
  "costInPence" : 2600
}, {
  "orderNo" : "5CC20E0B",
  "orderStatus" : "DELIVERED",
  "orderValidationCode" : "NO_ERROR",
  "costInPence" : 2400
}, {
  "orderNo" : "473706E0",
  "orderStatus" : "DELIVERED",
  "orderValidationCode" : "NO_ERROR",
  "costInPence" : 2400
}, {
  "orderNo" : "1B911AE4",
  "orderStatus" : "DELIVERED",
  "orderValidationCode" : "NO_ERROR",
  "costInPence" : 2500
}, {
  "orderNo" : "4592A061",
  "orderStatus" : "INVALID",
  "orderValidationCode" : "RESTAURANT_CLOSED",
  "costInPence" : 2600
}, {
  "orderNo" : "765E9084",
  "orderStatus" : "DELIVERED",
  "orderValidationCode" : "NO_ERROR",
  "costInPence" : 2400
}, {
  "orderNo" : "21F15AF8",
  "orderStatus" : "DELIVERED",
  "orderValidationCode" : "NO_ERROR",
  "costInPence" : 2400
}, {
  "orderNo" : "0E6F171C",
  "orderStatus" : "DELIVERED",
  "orderValidationCode" : "NO_ERROR",
  "costInPence" : 2500
}, {
  "orderNo" : "466B1A5A",
  "orderStatus" : "INVALID",
  "orderValidationCode" : "RESTAURANT_CLOSED",
  "costInPence" : 2600
}, {
  "orderNo" : "70BE8F96",
  "orderStatus" : "DELIVERED",
  "orderValidationCode" : "NO_ERROR",
  "costInPence" : 2400
}, {
  "orderNo" : "2BC6BC67",
  "orderStatus" : "DELIVERED",
  "orderValidationCode" : "NO_ERROR",
  "costInPence" : 2400
}, {
  "orderNo" : "24408ED9",
  "orderStatus" : "DELIVERED",
  "orderValidationCode" : "NO_ERROR",
  "costInPence" : 2500
}, {
  "orderNo" : "622A80F6",
  "orderStatus" : "INVALID",
  "orderValidationCode" : "RESTAURANT_CLOSED",
  "costInPence" : 2600
}, {
  "orderNo" : "648285A1",
  "orderStatus" : "DELIVERED",
  "orderValidationCode" : "NO_ERROR",
  "costInPence" : 2400
}, {
  "orderNo" : "288F014F",
  "orderStatus" : "DELIVERED",
  "orderValidationCode" : "NO_ERROR",
  "costInPence" : 2400
} ]